ckanext_mongodatastore-0.4-py2.7-nspkg.pth
ckanext/landingpageview/__init__.py
ckanext/landingpageview/plugin.py
ckanext/mongodatastore/__init__.py
ckanext/mongodatastore/blueprint.py
ckanext/mongodatastore/cli.py
ckanext/mongodatastore/datastore_backend.py
ckanext/mongodatastore/exceptions.py
ckanext/mongodatastore/model.py
ckanext/mongodatastore/plugin.py
ckanext/mongodatastore/preprocessor.py
ckanext/mongodatastore/util.py
ckanext/mongodatastore/controller/__init__.py
ckanext/mongodatastore/controller/mongodb.py
ckanext/mongodatastore/controller/querystore.py
ckanext/mongodatastore/logic/__init__.py
ckanext/mongodatastore/logic/action.py
ckanext/mongodatastore/tests/__init__.py
ckanext/mongodatastore/tests/test_mongodb_controller.py
ckanext/mongodatastore/tests/test_preprocessor.py
ckanext/mongodatastore/tests/test_util.py
ckanext/mongodatastore/theme/__init__.py
ckanext/mongodatastore/theme/public/__init__.py
ckanext/mongodatastore/theme/public/resource.config
ckanext/mongodatastore/theme/public/css/datatables.css
ckanext/mongodatastore/theme/public/css/datatables.min.css
ckanext/mongodatastore/theme/public/js/datatables.js
ckanext/mongodatastore/theme/public/js/datatables.min.js
ckanext/mongodatastore/theme/public/js/datatablesview.js
ckanext/mongodatastore/theme/templates/home/layout1.html
ckanext/mongodatastore/theme/templates/home/snippets/pid_resolve_form.html
ckanext/mongodatastore/theme/templates/home/snippets/promoted.html
ckanext/mongodatastore/theme/templates/mongodatastore/query_view.html
ckanext/mongodatastore/theme/templates/mongodatastore/citation_template/standard_citation.html
ckanext/reclinecitationview/__init__.py
ckanext/reclinecitationview/plugin.py
ckanext_mongodatastore-0.4.dist-info/LICENSE
ckanext_mongodatastore-0.4.dist-info/METADATA
ckanext_mongodatastore-0.4.dist-info/WHEEL
ckanext_mongodatastore-0.4.dist-info/entry_points.txt
ckanext_mongodatastore-0.4.dist-info/namespace_packages.txt
ckanext_mongodatastore-0.4.dist-info/top_level.txt
ckanext_mongodatastore-0.4.dist-info/RECORD
