Metadata-Version: 2.1
Name: ckanext-mongodatastore
Version: 0.4
Summary: A MongoDB DataStoreBackend implementation, that supports data citation.
Home-page: https://github.com/fwoerister/ckanext-mongodatastore
Author: Florian Woerister
Author-email: florian.woerister@tuwien.ac.at
License: AGPLv3+
Keywords: CKAN mongodb datastore datacitation citation
Platform: UNKNOWN
Classifier: Development Status :: 4 - Beta
Classifier: License :: OSI Approved :: GNU Affero General Public License v3 or later (AGPLv3+)
Classifier: Programming Language :: Python :: 3
